[
  {
    "id": "cuet-hist-col-41",
    "options": [
      {
        "key": "A",
        "text": "A system where peasants collectively decided the revenue amount",
        "is_correct": false
      },
      {
        "key": "B",
        "text": "A system where the right to collect revenue was auctioned to the highest bidder for a fixed period",
        "is_correct": true
      },
      {
        "key": "C",
        "text": "A system where revenue was paid in the form of agricultural produce only",
        "is_correct": false
      },
      {
        "key": "D",
        "text": "A system where the British Crown directly collected taxes door-to-door",
        "is_correct": false
      }
    ],
    "correct_answer": "B",
    "explanation": "Before the Permanent Settlement, the Company experimented with revenue farming — auctioning the right to collect revenue from a district to the highest bidder for short terms (often five years). This led to rack-renting and exploitation as revenue farmers tried to extract maximum revenue quickly.",
    "difficulty": "medium",
    "bloom_level": "understand",
    "subject": "history",
    "chapter_id": "cuet-hist-colonialism",
    "chapter": "Colonialism and the Countryside",
    "topic": "Colonialism and the Countryside",
    "exam_suitability": [
      "CUET"
    ],
    "question_text": "What was the 'revenue farming' system that preceded the Permanent Settlement in Bengal?",
    "question_type": "mcq",
    "elimination_hints": [],
    "concept_tags": [],
    "subtopic": ""
  },
  {
    "id": "cuet-hist-col-42",
    "options": [
      {
        "key": "A",
        "text": "That zamindars would flee to other countries",
        "is_correct": false
      },
      {
        "key": "B",
        "text": "That zamindars, as proprietors with a permanent stake, would invest in improving agriculture like English landlords",
        "is_correct": true
      },
      {
        "key": "C",
        "text": "That peasants would stop cultivating land entirely",
        "is_correct": false
      },
      {
        "key": "D",
        "text": "That the Company would not need any revenue from Bengal",
        "is_correct": false
      }
    ],
    "correct_answer": "B",
    "explanation": "The British modelled the Permanent Settlement on English landlordism, assuming that secure property rights and a fixed demand would incentivise zamindars to invest in land improvement. In practice, most zamindars became absentee rent collectors rather than improving landlords.",
    "difficulty": "medium",
    "bloom_level": "analyse",
    "subject": "history",
    "chapter_id": "cuet-hist-colonialism",
    "chapter": "Colonialism and the Countryside",
    "topic": "Colonialism and the Countryside",
    "exam_suitability": [
      "CUET"
    ],
    "question_text": "Which of the following was a key assumption behind the Permanent Settlement that ultimately proved incorrect?",
    "question_type": "mcq",
    "elimination_hints": [],
    "concept_tags": [],
    "subtopic": ""
  },
  {
    "id": "cuet-hist-col-43",
    "options": [
      {
        "key": "A",
        "text": "Land became more productive due to more managers",
        "is_correct": false
      },
      {
        "key": "B",
        "text": "Multiple layers of intermediary tenure-holders emerged between the zamindar and the actual cultivator, each extracting a share of the rent",
        "is_correct": true
      },
      {
        "key": "C",
        "text": "Peasants gained more rights as more people shared responsibility",
        "is_correct": false
      },
      {
        "key": "D",
        "text": "The British abolished the zamindari system in response",
        "is_correct": false
      }
    ],
    "correct_answer": "B",
    "explanation": "Zamindars sublet portions of their estates, and those sub-lessees further sublet, creating chains of intermediary tenure-holders. Each layer extracted rent from those below, meaning the actual cultivator paid far more than what reached the zamindar or the state.",
    "difficulty": "hard",
    "bloom_level": "analyse",
    "subject": "history",
    "chapter_id": "cuet-hist-colonialism",
    "chapter": "Colonialism and the Countryside",
    "topic": "Colonialism and the Countryside",
    "exam_suitability": [
      "CUET"
    ],
    "question_text": "What was the consequence of the 'sub-infeudation' that developed under the Permanent Settlement in Bengal?",
    "question_type": "mcq",
    "elimination_hints": [],
    "concept_tags": [],
    "subtopic": ""
  },
  {
    "id": "cuet-hist-col-44",
    "options": [
      {
        "key": "A",
        "text": "Birsa Munda and Tilka Manjhi",
        "is_correct": false
      },
      {
        "key": "B",
        "text": "Sidhu and Kanhu Murmu",
        "is_correct": true
      },
      {
        "key": "C",
        "text": "Tantia Tope and Nana Sahib",
        "is_correct": false
      },
      {
        "key": "D",
        "text": "Alluri Sitarama Raju",
        "is_correct": false
      }
    ],
    "correct_answer": "B",
    "explanation": "The Santhal Rebellion was led by two brothers, Sidhu Murmu and Kanhu Murmu. They mobilised thousands of Santhals against the dikus (outsiders) and the colonial administration. The rebellion was eventually suppressed with significant military force.",
    "difficulty": "easy",
    "bloom_level": "remember",
    "subject": "history",
    "chapter_id": "cuet-hist-colonialism",
    "chapter": "Colonialism and the Countryside",
    "topic": "Colonialism and the Countryside",
    "exam_suitability": [
      "CUET"
    ],
    "question_text": "Who led the Santhal Rebellion (Hool) of 1855–56?",
    "question_type": "mcq",
    "elimination_hints": [],
    "concept_tags": [],
    "subtopic": ""
  },
  {
    "id": "cuet-hist-col-45",
    "options": [
      {
        "key": "A",
        "text": "They were deported to the Andaman Islands",
        "is_correct": false
      },
      {
        "key": "B",
        "text": "The British created the separate Santhal Pargana district to administer them directly, with some protective regulations",
        "is_correct": true
      },
      {
        "key": "C",
        "text": "They were absorbed into the Bengal zamindari system with full rights",
        "is_correct": false
      },
      {
        "key": "D",
        "text": "Nothing changed; conditions remained exactly as before the rebellion",
        "is_correct": false
      }
    ],
    "correct_answer": "B",
    "explanation": "After suppressing the rebellion, the British carved out the Santhal Pargana as a separate administrative district in 1856. Special regulations were introduced to limit the exploitation of Santhals by outsiders, though these protections were imperfect in practice.",
    "difficulty": "medium",
    "bloom_level": "remember",
    "subject": "history",
    "chapter_id": "cuet-hist-colonialism",
    "chapter": "Colonialism and the Countryside",
    "topic": "Colonialism and the Countryside",
    "exam_suitability": [
      "CUET"
    ],
    "question_text": "What happened to the Santhals after the British suppressed the Hool of 1855–56?",
    "question_type": "mcq",
    "elimination_hints": [],
    "concept_tags": [],
    "subtopic": ""
  },
  {
    "id": "cuet-hist-col-46",
    "options": [
      {
        "key": "A",
        "text": "They maintained transparent digital records accessible to all",
        "is_correct": false
      },
      {
        "key": "B",
        "text": "They manipulated account books by inflating interest, adding fictitious charges, and getting illiterate peasants to sign blank or fraudulent bonds",
        "is_correct": true
      },
      {
        "key": "C",
        "text": "They reduced debts voluntarily to maintain goodwill",
        "is_correct": false
      },
      {
        "key": "D",
        "text": "They kept no records at all, relying on verbal agreements",
        "is_correct": false
      }
    ],
    "correct_answer": "B",
    "explanation": "Moneylenders exploited peasant illiteracy by maintaining manipulated accounts — inflating interest rates, adding service charges, and tricking peasants into signing bonds for amounts far exceeding the actual loan. This systematic fraud was a major driver of peasant indebtedness.",
    "difficulty": "medium",
    "bloom_level": "understand",
    "subject": "history",
    "chapter_id": "cuet-hist-colonialism",
    "chapter": "Colonialism and the Countryside",
    "topic": "Colonialism and the Countryside",
    "exam_suitability": [
      "CUET"
    ],
    "question_text": "How did moneylenders in the Bombay Deccan typically manipulate debt records to their advantage?",
    "question_type": "mcq",
    "elimination_hints": [],
    "concept_tags": [],
    "subtopic": ""
  },
  {
    "id": "cuet-hist-col-47",
    "options": [
      {
        "key": "A",
        "text": "Peasants continued to grow only traditional food grains as before",
        "is_correct": false
      },
      {
        "key": "B",
        "text": "The demand for cash payment of revenue pushed peasants towards growing cash crops and integrating into commercial markets",
        "is_correct": true
      },
      {
        "key": "C",
        "text": "Peasants abandoned agriculture entirely and took up handicrafts",
        "is_correct": false
      },
      {
        "key": "D",
        "text": "The British banned all cash crop cultivation to protect food supply",
        "is_correct": false
      }
    ],
    "correct_answer": "B",
    "explanation": "Since colonial revenue had to be paid in cash, peasants were forced to sell their produce or grow cash crops (cotton, indigo, opium, sugarcane) that could be sold readily. This commercialisation of agriculture fundamentally altered traditional cropping patterns.",
    "difficulty": "easy",
    "bloom_level": "understand",
    "subject": "history",
    "chapter_id": "cuet-hist-colonialism",
    "chapter": "Colonialism and the Countryside",
    "topic": "Colonialism and the Countryside",
    "exam_suitability": [
      "CUET"
    ],
    "question_text": "What was the impact of colonial revenue policies on the pattern of crop cultivation in India?",
    "question_type": "mcq",
    "elimination_hints": [],
    "concept_tags": [],
    "subtopic": ""
  },
  {
    "id": "cuet-hist-col-48",
    "options": [
      {
        "key": "A",
        "text": "Zamindars voluntarily sold their estates to invest in shipping",
        "is_correct": false
      },
      {
        "key": "B",
        "text": "When zamindars defaulted on revenue, their estates were auctioned and urban commercial groups with ready cash bought them as investments",
        "is_correct": true
      },
      {
        "key": "C",
        "text": "The British specifically reserved auction rights for merchants only",
        "is_correct": false
      },
      {
        "key": "D",
        "text": "Peasants pooled their resources and bought the estates collectively",
        "is_correct": false
      }
    ],
    "correct_answer": "B",
    "explanation": "The Sunset Law caused frequent zamindari auctions. Urban merchants, bankers, and traders — who had liquid capital — purchased these estates as revenue-yielding investments. This transferred land control from traditional rural elites to urban commercial classes with no interest in agriculture.",
    "difficulty": "medium",
    "bloom_level": "analyse",
    "subject": "history",
    "chapter_id": "cuet-hist-colonialism",
    "chapter": "Colonialism and the Countryside",
    "topic": "Colonialism and the Countryside",
    "exam_suitability": [
      "CUET"
    ],
    "question_text": "Why did many zamindari estates in Bengal end up being purchased by merchants, traders, and moneylenders at auction?",
    "question_type": "mcq",
    "elimination_hints": [],
    "concept_tags": [],
    "subtopic": ""
  },
  {
    "id": "cuet-hist-col-49",
    "options": [
      {
        "key": "A",
        "text": "Only the Ain-i-Akbari",
        "is_correct": false
      },
      {
        "key": "B",
        "text": "Petition records, vernacular newspapers, Deccan Riots Commission testimony, and revenue settlement reports",
        "is_correct": true
      },
      {
        "key": "C",
        "text": "Ancient Sanskrit texts from the Gupta period",
        "is_correct": false
      },
      {
        "key": "D",
        "text": "Only European travellers' accounts from the 17th century",
        "is_correct": false
      }
    ],
    "correct_answer": "B",
    "explanation": "Historians use a variety of sources — peasant petitions to officials, Marathi newspapers, oral testimonies recorded by the Deccan Riots Commission, revenue settlement records, and court documents — to reconstruct the peasant experience beyond the official colonial narrative.",
    "difficulty": "medium",
    "bloom_level": "remember",
    "subject": "history",
    "chapter_id": "cuet-hist-colonialism",
    "chapter": "Colonialism and the Countryside",
    "topic": "Colonialism and the Countryside",
    "exam_suitability": [
      "CUET"
    ],
    "question_text": "What sources do historians use alongside official British records to study the Deccan peasant experience?",
    "question_type": "mcq",
    "elimination_hints": [],
    "concept_tags": [],
    "subtopic": ""
  },
  {
    "id": "cuet-hist-col-50",
    "options": [
      {
        "key": "A",
        "text": "He praised the Paharias as a model civilisation",
        "is_correct": false
      },
      {
        "key": "B",
        "text": "He viewed them through a colonial lens, describing them as primitive, wild, and in need of 'civilising' through settled agriculture",
        "is_correct": true
      },
      {
        "key": "C",
        "text": "He recommended that the Paharias be given full self-governance",
        "is_correct": false
      },
      {
        "key": "D",
        "text": "He had no opinion about the Paharias and only recorded botanical data",
        "is_correct": false
      }
    ],
    "correct_answer": "B",
    "explanation": "Buchanan's surveys, while valuable for their detail, reflected colonial attitudes. He described hill and forest communities like the Paharias as 'wild' and 'uncivilised', measuring progress by the standard of settled agriculture — a perspective that justified colonial intervention in their lives.",
    "difficulty": "hard",
    "bloom_level": "analyse",
    "subject": "history",
    "chapter_id": "cuet-hist-colonialism",
    "chapter": "Colonialism and the Countryside",
    "topic": "Colonialism and the Countryside",
    "exam_suitability": [
      "CUET"
    ],
    "question_text": "How did Francis Buchanan's surveys reflect the colonial perspective on tribal communities like the Paharias?",
    "question_type": "mcq",
    "elimination_hints": [],
    "concept_tags": [],
    "subtopic": ""
  },
  {
    "id": "cuet-hist-col-51",
    "options": [
      {
        "key": "A",
        "text": "A revolt by indigo planters against the British in 1757",
        "is_correct": false
      },
      {
        "key": "B",
        "text": "An uprising by Bengali peasants against forced indigo cultivation by European planters in 1859–60",
        "is_correct": true
      },
      {
        "key": "C",
        "text": "A rebellion by Santhal indigo farmers in 1875",
        "is_correct": false
      },
      {
        "key": "D",
        "text": "A strike by indigo factory workers in Bombay in 1905",
        "is_correct": false
      }
    ],
    "correct_answer": "B",
    "explanation": "The Indigo Revolt (Nil Bidroha) of 1859–60 was a peasant uprising in Bengal against the oppressive indigo plantation system. European planters forced peasants to grow indigo under exploitative terms, prompting widespread resistance and refusal to cultivate the crop.",
    "difficulty": "easy",
    "bloom_level": "remember",
    "subject": "history",
    "chapter_id": "cuet-hist-colonialism",
    "chapter": "Colonialism and the Countryside",
    "topic": "Colonialism and the Countryside",
    "exam_suitability": [
      "CUET"
    ],
    "question_text": "What was the 'indigo revolt' and when did it take place?",
    "question_type": "mcq",
    "elimination_hints": [],
    "concept_tags": [],
    "subtopic": ""
  },
  {
    "id": "cuet-hist-col-52",
    "options": [
      {
        "key": "A",
        "text": "Purely for academic geographical knowledge",
        "is_correct": false
      },
      {
        "key": "B",
        "text": "To understand, classify, and control land, people, and resources for more efficient revenue extraction and administration",
        "is_correct": true
      },
      {
        "key": "C",
        "text": "To help Indian farmers improve their agricultural techniques",
        "is_correct": false
      },
      {
        "key": "D",
        "text": "To plan the construction of tourist resorts in rural areas",
        "is_correct": false
      }
    ],
    "correct_answer": "B",
    "explanation": "Colonial surveys (like Buchanan's) served administrative and revenue purposes. By mapping terrain, cataloguing resources, classifying communities, and documenting land use, the colonial state could design revenue systems, settle populations, and extend its control over the countryside more effectively.",
    "difficulty": "easy",
    "bloom_level": "understand",
    "subject": "history",
    "chapter_id": "cuet-hist-colonialism",
    "chapter": "Colonialism and the Countryside",
    "topic": "Colonialism and the Countryside",
    "exam_suitability": [
      "CUET"
    ],
    "question_text": "Which of the following best explains why the British colonial state was interested in conducting detailed surveys and mapping of the Indian countryside?",
    "question_type": "mcq",
    "elimination_hints": [],
    "concept_tags": [],
    "subtopic": ""
  },
  {
    "id": "cuet-hist-col-53",
    "options": [
      {
        "key": "A",
        "text": "Women gained complete economic independence",
        "is_correct": false
      },
      {
        "key": "B",
        "text": "Women's labour intensified as families worked harder to meet revenue demands and repay debts, yet their contributions remained largely unrecognised in official records",
        "is_correct": true
      },
      {
        "key": "C",
        "text": "Women stopped participating in agriculture entirely",
        "is_correct": false
      },
      {
        "key": "D",
        "text": "Colonial laws guaranteed equal property rights for women",
        "is_correct": false
      }
    ],
    "correct_answer": "B",
    "explanation": "Colonial revenue pressures intensified the workload for entire peasant families, including women. Women performed agricultural labour, processed crops, and contributed to household income, but colonial records focused on male cultivators, rendering women's contributions invisible.",
    "difficulty": "hard",
    "bloom_level": "analyse",
    "subject": "history",
    "chapter_id": "cuet-hist-colonialism",
    "chapter": "Colonialism and the Countryside",
    "topic": "Colonialism and the Countryside",
    "exam_suitability": [
      "CUET"
    ],
    "question_text": "How did the position of women in peasant households change under colonial economic pressures in the Deccan?",
    "question_type": "mcq",
    "elimination_hints": [],
    "concept_tags": [],
    "subtopic": ""
  },
  {
    "id": "cuet-hist-col-54",
    "options": [
      {
        "key": "A",
        "text": "It abolished all forms of moneylending in India",
        "is_correct": false
      },
      {
        "key": "B",
        "text": "It attempted to regulate the relationship between moneylenders and peasants by restricting the terms of debt contracts and preventing easy land transfers",
        "is_correct": true
      },
      {
        "key": "C",
        "text": "It granted land ownership to all Deccan peasants for free",
        "is_correct": false
      },
      {
        "key": "D",
        "text": "It increased the revenue demand on Deccan cultivators to compensate for riot damages",
        "is_correct": false
      }
    ],
    "correct_answer": "B",
    "explanation": "The Act aimed to protect Deccan peasants by limiting the ability of moneylenders to use the courts for debt recovery, restricting compound interest, and making it harder to transfer peasant land to creditors. However, its effectiveness was limited as moneylenders found ways around its provisions.",
    "difficulty": "medium",
    "bloom_level": "understand",
    "subject": "history",
    "chapter_id": "cuet-hist-colonialism",
    "chapter": "Colonialism and the Countryside",
    "topic": "Colonialism and the Countryside",
    "exam_suitability": [
      "CUET"
    ],
    "question_text": "What was the significance of the Deccan Agriculturists' Relief Act of 1879?",
    "question_type": "mcq",
    "elimination_hints": [],
    "concept_tags": [],
    "subtopic": ""
  },
  {
    "id": "cuet-hist-col-55",
    "options": [
      {
        "key": "A",
        "text": "Forest laws gave them complete ownership of forests",
        "is_correct": false
      },
      {
        "key": "B",
        "text": "Colonial forest laws restricted their access to forests for shifting cultivation, hunting, and gathering, undermining their traditional livelihoods",
        "is_correct": true
      },
      {
        "key": "C",
        "text": "Forest laws had no impact on any community",
        "is_correct": false
      },
      {
        "key": "D",
        "text": "Forest laws encouraged them to expand their traditional practices",
        "is_correct": false
      }
    ],
    "correct_answer": "B",
    "explanation": "The British classified forests as state property and imposed restrictions on access, burning, and cultivation within them. This directly undermined the livelihoods of communities like the Paharias who depended on forests for shifting cultivation, hunting, gathering, and grazing.",
    "difficulty": "easy",
    "bloom_level": "understand",
    "subject": "history",
    "chapter_id": "cuet-hist-colonialism",
    "chapter": "Colonialism and the Countryside",
    "topic": "Colonialism and the Countryside",
    "exam_suitability": [
      "CUET"
    ],
    "question_text": "What was the impact of colonial forest laws on communities like the Paharias and other forest-dwelling groups?",
    "question_type": "mcq",
    "elimination_hints": [],
    "concept_tags": [],
    "subtopic": ""
  },
  {
    "id": "cuet-hist-col-56",
    "options": [
      {
        "key": "A",
        "text": "Because the report is written in an ancient language no one can read",
        "is_correct": false
      },
      {
        "key": "B",
        "text": "Because such reports were produced within specific political contexts and carried biases of their authors, serving particular agendas in British politics",
        "is_correct": true
      },
      {
        "key": "C",
        "text": "Because the report contains only fictional stories",
        "is_correct": false
      },
      {
        "key": "D",
        "text": "Because the report was never actually submitted to Parliament",
        "is_correct": false
      }
    ],
    "correct_answer": "B",
    "explanation": "The Fifth Report was produced by individuals with political motivations — critics of the Company seeking greater Parliamentary oversight. It emphasised failures and abuses. Historians must account for these biases, cross-reference with other sources, and distinguish fact from political framing.",
    "difficulty": "medium",
    "bloom_level": "analyse",
    "subject": "history",
    "chapter_id": "cuet-hist-colonialism",
    "chapter": "Colonialism and the Countryside",
    "topic": "Colonialism and the Countryside",
    "exam_suitability": [
      "CUET"
    ],
    "question_text": "Why do historians need to read sources like the Fifth Report critically rather than accepting them at face value?",
    "question_type": "mcq",
    "elimination_hints": [],
    "concept_tags": [],
    "subtopic": ""
  },
  {
    "id": "cuet-hist-col-57",
    "options": [
      {
        "key": "A",
        "text": "Railways had no impact on agriculture",
        "is_correct": false
      },
      {
        "key": "B",
        "text": "Railways facilitated the transport of cash crops to ports for export, deepening the integration of Indian agriculture into global markets",
        "is_correct": true
      },
      {
        "key": "C",
        "text": "Railways only transported British manufactured goods, not agricultural produce",
        "is_correct": false
      },
      {
        "key": "D",
        "text": "Railways led to the decline of all commercial farming",
        "is_correct": false
      }
    ],
    "correct_answer": "B",
    "explanation": "The expansion of railways from the 1850s made it economically viable to transport bulky agricultural produce (cotton, wheat, jute, indigo) to port cities for export. This infrastructure accelerated the shift from subsistence to commercial agriculture across the Indian countryside.",
    "difficulty": "easy",
    "bloom_level": "understand",
    "subject": "history",
    "chapter_id": "cuet-hist-colonialism",
    "chapter": "Colonialism and the Countryside",
    "topic": "Colonialism and the Countryside",
    "exam_suitability": [
      "CUET"
    ],
    "question_text": "What was the relationship between the expansion of railways in India and the commercialisation of agriculture?",
    "question_type": "mcq",
    "elimination_hints": [],
    "concept_tags": [],
    "subtopic": ""
  },
  {
    "id": "cuet-hist-col-58",
    "options": [
      {
        "key": "A",
        "text": "They were wealthy landowners who employed labourers",
        "is_correct": false
      },
      {
        "key": "B",
        "text": "They cultivated land belonging to others and paid a share (often half) of the produce as rent, leaving them impoverished",
        "is_correct": true
      },
      {
        "key": "C",
        "text": "They were British-appointed revenue collectors",
        "is_correct": false
      },
      {
        "key": "D",
        "text": "They owned large estates under the Permanent Settlement",
        "is_correct": false
      }
    ],
    "correct_answer": "B",
    "explanation": "Bargadars were sharecroppers who cultivated land owned by zamindars or jotedars, surrendering a large share (typically half or more) of the harvest as rent. With no ownership rights and heavy rent burdens, most bargadars remained among the poorest sections of rural society.",
    "difficulty": "medium",
    "bloom_level": "understand",
    "subject": "history",
    "chapter_id": "cuet-hist-colonialism",
    "chapter": "Colonialism and the Countryside",
    "topic": "Colonialism and the Countryside",
    "exam_suitability": [
      "CUET"
    ],
    "question_text": "Which of the following best describes the condition of 'bargadars' (sharecroppers) in colonial Bengal?",
    "question_type": "mcq",
    "elimination_hints": [],
    "concept_tags": [],
    "subtopic": ""
  },
  {
    "id": "cuet-hist-col-59",
    "options": [
      {
        "key": "A",
        "text": "Genuine humanitarian concern for tribal welfare",
        "is_correct": false
      },
      {
        "key": "B",
        "text": "To secure trade routes, expand the revenue base, and prevent raids on settled plains by bringing these communities under administrative control",
        "is_correct": true
      },
      {
        "key": "C",
        "text": "To recruit hill tribes for the British navy",
        "is_correct": false
      },
      {
        "key": "D",
        "text": "To establish botanical gardens in the hills",
        "is_correct": false
      }
    ],
    "correct_answer": "B",
    "explanation": "British 'pacification' was driven by strategic and economic motives: securing trade routes through hill areas, stopping raids on settled agriculture, expanding cultivable land and the revenue base, and extending state authority into previously uncontrolled territories.",
    "difficulty": "medium",
    "bloom_level": "analyse",
    "subject": "history",
    "chapter_id": "cuet-hist-colonialism",
    "chapter": "Colonialism and the Countryside",
    "topic": "Colonialism and the Countryside",
    "exam_suitability": [
      "CUET"
    ],
    "question_text": "What was the primary reason behind the British policy of 'pacifying' hill and forest communities during the early 19th century?",
    "question_type": "mcq",
    "elimination_hints": [],
    "concept_tags": [],
    "subtopic": ""
  },
  {
    "id": "cuet-hist-col-60",
    "options": [
      {
        "key": "A",
        "text": "Revenue was collected directly from the ryot (cultivator)",
        "is_correct": false
      },
      {
        "key": "B",
        "text": "Revenue demand was periodically revised",
        "is_correct": false
      },
      {
        "key": "C",
        "text": "The revenue demand was fixed permanently and could never be increased",
        "is_correct": true
      },
      {
        "key": "D",
        "text": "Government officials surveyed and assessed each plot individually",
        "is_correct": false
      }
    ],
    "correct_answer": "C",
    "explanation": "Permanent fixation of revenue was a feature of the Permanent Settlement, not the Ryotwari system. Under Ryotwari, revenue was assessed on individual plots after survey and was subject to periodic revision (typically every 30 years), often resulting in increased demands.",
    "difficulty": "easy",
    "bloom_level": "understand",
    "subject": "history",
    "chapter_id": "cuet-hist-colonialism",
    "chapter": "Colonialism and the Countryside",
    "topic": "Colonialism and the Countryside",
    "exam_suitability": [
      "CUET"
    ],
    "question_text": "Which of the following was NOT a feature of the Ryotwari system as implemented in the Bombay Deccan?",
    "question_type": "mcq",
    "elimination_hints": [],
    "concept_tags": [],
    "subtopic": ""
  },
  {
    "id": "cuet-hist-col-61",
    "options": [
      {
        "key": "A",
        "text": "Both A and R are true and R is the correct explanation of A",
        "is_correct": false
      },
      {
        "key": "B",
        "text": "Both A and R are true but R is NOT the correct explanation of A",
        "is_correct": false
      },
      {
        "key": "C",
        "text": "A is true but R is false",
        "is_correct": false
      },
      {
        "key": "D",
        "text": "A is false but R is true",
        "is_correct": true
      }
    ],
    "correct_answer": "D",
    "explanation": "The cotton boom did not permanently improve peasant conditions (A is incorrect). The price crash after the American Civil War ended (R is correct) left farmers who had borrowed heavily to expand cotton cultivation deeply in debt, worsening their condition rather than improving it.",
    "difficulty": "medium",
    "bloom_level": "analyse",
    "subject": "history",
    "chapter_id": "cuet-hist-colonialism",
    "chapter": "Colonialism and the Countryside",
    "topic": "Colonialism and the Countryside",
    "exam_suitability": [
      "CUET"
    ],
    "question_text": "Assertion (A): The cotton boom of the 1860s in the Bombay Deccan permanently improved the economic condition of peasants.\nReason (R): The end of the American Civil War in 1865 led to a collapse of Indian cotton prices as American cotton re-entered global markets.\n\nChoose the correct option:",
    "question_type": "assertion-reasoning",
    "elimination_hints": [],
    "concept_tags": [],
    "subtopic": ""
  },
  {
    "id": "cuet-hist-col-62",
    "options": [
      {
        "key": "A",
        "text": "Both A and R are true and R is the correct explanation of A",
        "is_correct": false
      },
      {
        "key": "B",
        "text": "Both A and R are true but R is NOT the correct explanation of A",
        "is_correct": false
      },
      {
        "key": "C",
        "text": "A is true but R is false",
        "is_correct": false
      },
      {
        "key": "D",
        "text": "A is false but R is true",
        "is_correct": true
      }
    ],
    "correct_answer": "D",
    "explanation": "Jotedars generally did not support zamindars (A is incorrect). R correctly states that jotedars, being powerful local figures, often resisted zamindari authority by withholding revenue, encouraging ryot non-payment, and purchasing auctioned estates — thereby undermining the zamindars' position.",
    "difficulty": "hard",
    "bloom_level": "analyse",
    "subject": "history",
    "chapter_id": "cuet-hist-colonialism",
    "chapter": "Colonialism and the Countryside",
    "topic": "Colonialism and the Countryside",
    "exam_suitability": [
      "CUET"
    ],
    "question_text": "Assertion (A): The jotedars of Bengal supported the zamindars in collecting revenue from peasants.\nReason (R): Jotedars were wealthy peasants who often resisted zamindar authority and mobilised ryots to delay or withhold revenue payment.\n\nChoose the correct option:",
    "question_type": "assertion-reasoning",
    "elimination_hints": [],
    "concept_tags": [],
    "subtopic": ""
  },
  {
    "id": "cuet-hist-col-63",
    "options": [
      {
        "key": "A",
        "text": "True",
        "is_correct": false
      },
      {
        "key": "B",
        "text": "False",
        "is_correct": true
      }
    ],
    "correct_answer": "False",
    "explanation": "This is false. The Paharias, the original hill inhabitants, were displaced and marginalised as the British encouraged Santhal settlement in the foothills and lower areas. The Paharias retreated deeper into the hills and there was conflict rather than cooperation between the two groups.",
    "difficulty": "easy",
    "bloom_level": "understand",
    "subject": "history",
    "chapter_id": "cuet-hist-colonialism",
    "chapter": "Colonialism and the Countryside",
    "topic": "Colonialism and the Countryside",
    "exam_suitability": [
      "CUET"
    ],
    "question_text": "State whether the following statement is True or False:\n\n'The Paharias and the Santhals had a harmonious and cooperative relationship in the Rajmahal Hills during the colonial period.'",
    "question_type": "true-false",
    "elimination_hints": [],
    "concept_tags": [],
    "subtopic": ""
  },
  {
    "id": "cuet-hist-col-64",
    "options": [
      {
        "key": "A",
        "text": "Famine",
        "is_correct": false
      },
      {
        "key": "B",
        "text": "Deccan Riots",
        "is_correct": true
      },
      {
        "key": "C",
        "text": "Hunter",
        "is_correct": false
      },
      {
        "key": "D",
        "text": "Simon",
        "is_correct": false
      }
    ],
    "correct_answer": "B",
    "explanation": "The Deccan Riots Commission was appointed in 1875 to investigate the causes of the peasant uprising in the Bombay Deccan. Its findings — highlighting chronic peasant indebtedness and moneylender exploitation — led to the passage of the Deccan Agriculturists' Relief Act, 1879.",
    "difficulty": "easy",
    "bloom_level": "remember",
    "subject": "history",
    "chapter_id": "cuet-hist-colonialism",
    "chapter": "Colonialism and the Countryside",
    "topic": "Colonialism and the Countryside",
    "exam_suitability": [
      "CUET"
    ],
    "question_text": "Fill in the blank:\n\nThe ________ Commission was appointed by the British government to investigate the causes of the 1875 Deccan Riots.",
    "question_type": "fill-in-blanks",
    "elimination_hints": [],
    "concept_tags": [],
    "subtopic": ""
  },
  {
    "id": "cuet-hist-col-65",
    "options": [
      {
        "key": "A",
        "text": "1-c, 2-a, 3-d, 4-b",
        "is_correct": true
      },
      {
        "key": "B",
        "text": "1-a, 2-c, 3-b, 4-d",
        "is_correct": false
      },
      {
        "key": "C",
        "text": "1-d, 2-b, 3-a, 4-c",
        "is_correct": false
      },
      {
        "key": "D",
        "text": "1-b, 2-d, 3-c, 4-a",
        "is_correct": false
      }
    ],
    "correct_answer": "A",
    "explanation": "Paharias were marginalised into the hills (c); Santhals settled in Damin-i-Koh and later rebelled (a); Deccan ryots were indebted to sahukars and revolted in 1875 (d); Bengal zamindars lost estates through auctions (b).",
    "difficulty": "medium",
    "bloom_level": "understand",
    "subject": "history",
    "chapter_id": "cuet-hist-colonialism",
    "chapter": "Colonialism and the Countryside",
    "topic": "Colonialism and the Countryside",
    "exam_suitability": [
      "CUET"
    ],
    "question_text": "Match the following communities/groups with their experiences under colonial rule in rural India:\n\nCommunities:\n1. Paharias\n2. Santhals\n3. Deccan ryots\n4. Bengal zamindars\n\nExperiences:\n(a) Settled in the Damin-i-Koh, later rebelled against dikus in 1855–56\n(b) Lost estates through the Sunset Law and auction system\n(c) Pushed deeper into the Rajmahal Hills as outsiders settled in their territory\n(d) Trapped in debt cycles by sahukars and revolted in 1875",
    "question_type": "match-the-following",
    "elimination_hints": [],
    "concept_tags": [],
    "subtopic": "",
    "payload": {
      "column_a": [
        {
          "id": "1",
          "text": "Paharias"
        },
        {
          "id": "2",
          "text": "Santhals"
        },
        {
          "id": "3",
          "text": "Deccan ryots"
        },
        {
          "id": "4",
          "text": "Bengal zamindars"
        }
      ],
      "column_b": [
        {
          "id": "a",
          "text": "Settled in the Damin-i-Koh, later rebelled against dikus in 1855–56"
        },
        {
          "id": "b",
          "text": "Lost estates through the Sunset Law and auction system"
        },
        {
          "id": "c",
          "text": "Pushed deeper into the Rajmahal Hills as outsiders settled in their territory"
        },
        {
          "id": "d",
          "text": "Trapped in debt cycles by sahukars and revolted in 1875"
        }
      ]
    }
  },
  {
    "id": "cuet-hist-col-66",
    "options": [
      {
        "key": "A",
        "text": "1-b, 2-c, 3-d, 4-a",
        "is_correct": true
      },
      {
        "key": "B",
        "text": "1-c, 2-b, 3-a, 4-d",
        "is_correct": false
      },
      {
        "key": "C",
        "text": "1-a, 2-d, 3-c, 4-b",
        "is_correct": false
      },
      {
        "key": "D",
        "text": "1-d, 2-a, 3-b, 4-c",
        "is_correct": false
      }
    ],
    "correct_answer": "A",
    "explanation": "Fifth Report documents the impact of Permanent Settlement in Bengal (b); Deccan Riots Commission investigates peasant indebtedness in the Deccan (c); Buchanan's surveys describe hill communities in eastern India (d); Ain-i-Akbari records pre-colonial Mughal revenue administration (a).",
    "difficulty": "hard",
    "bloom_level": "analyse",
    "subject": "history",
    "chapter_id": "cuet-hist-colonialism",
    "chapter": "Colonialism and the Countryside",
    "topic": "Colonialism and the Countryside",
    "exam_suitability": [
      "CUET"
    ],
    "question_text": "Match the following historical sources with what they reveal about colonial India:\n\nSources:\n1. Fifth Report (1813)\n2. Deccan Riots Commission Report (1878)\n3. Buchanan's Surveys (early 1800s)\n4. Ain-i-Akbari (1595)\n\nInsights:\n(a) Pre-colonial Mughal agrarian administration and revenue system\n(b) Impact of Permanent Settlement and Company revenue administration in Bengal\n(c) Causes of peasant indebtedness and anti-moneylender violence in the Bombay Deccan\n(d) Colonial ethnographic descriptions of hill and forest communities in eastern India",
    "question_type": "match-the-following",
    "elimination_hints": [],
    "concept_tags": [],
    "subtopic": "",
    "payload": {
      "column_a": [
        {
          "id": "1",
          "text": "Fifth Report (1813)"
        },
        {
          "id": "2",
          "text": "Deccan Riots Commission Report (1878)"
        },
        {
          "id": "3",
          "text": "Buchanan's Surveys (early 1800s)"
        },
        {
          "id": "4",
          "text": "Ain-i-Akbari (1595)"
        }
      ],
      "column_b": [
        {
          "id": "a",
          "text": "Pre-colonial Mughal agrarian administration and revenue system"
        },
        {
          "id": "b",
          "text": "Impact of Permanent Settlement and Company revenue administration in Bengal"
        },
        {
          "id": "c",
          "text": "Causes of peasant indebtedness and anti-moneylender violence in the Bombay Deccan"
        },
        {
          "id": "d",
          "text": "Colonial ethnographic descriptions of hill and forest communities in eastern India"
        }
      ]
    }
  },
  {
    "id": "cuet-hist-col-67",
    "options": [
      {
        "key": "A",
        "text": "Accept the Fifth Report as entirely true because it was an official British document",
        "is_correct": false
      },
      {
        "key": "B",
        "text": "Accept the zamindar's petition as true because he had first-hand experience",
        "is_correct": false
      },
      {
        "key": "C",
        "text": "Recognise that both sources carry biases — the Fifth Report served a political agenda while the zamindar's petition was self-serving — and look for corroborating evidence from other sources",
        "is_correct": true
      },
      {
        "key": "D",
        "text": "Dismiss both sources as unreliable and conclude nothing can be known",
        "is_correct": false
      }
    ],
    "correct_answer": "C",
    "explanation": "This illustrates source criticism — a fundamental historical skill. The Fifth Report had political motives (criticising the Company), while the zamindar's petition was self-interested. A rigorous historian would cross-reference with revenue records, peasant petitions, and other evidence to build a more balanced picture.",
    "difficulty": "hard",
    "bloom_level": "analyse",
    "subject": "history",
    "chapter_id": "cuet-hist-colonialism",
    "chapter": "Colonialism and the Countryside",
    "topic": "Colonialism and the Countryside",
    "exam_suitability": [
      "CUET"
    ],
    "question_text": "Scenario: A student reads two accounts of the same Bengal district — one from the Fifth Report (1813) describing zamindari oppression and peasant misery, and another from a zamindar's petition to the Governor-General claiming he was a benevolent improving landlord who invested in irrigation.\n\nHow should the student approach these contradictory sources?",
    "question_type": "scenario-based",
    "elimination_hints": [],
    "concept_tags": [],
    "subtopic": ""
  },
  {
    "id": "cuet-hist-col-68",
    "options": [
      {
        "key": "A",
        "text": "The peasant was lazy and did not work hard enough",
        "is_correct": false
      },
      {
        "key": "B",
        "text": "A combination of volatile global commodity prices, exploitative interest rates, colonial courts enforcing debt contracts, and the lack of any peasant protection legislation at that time",
        "is_correct": true
      },
      {
        "key": "C",
        "text": "The British government directly seized the peasant's land for a railway",
        "is_correct": false
      },
      {
        "key": "D",
        "text": "The zamindar purchased the peasant's land at a fair price",
        "is_correct": false
      }
    ],
    "correct_answer": "B",
    "explanation": "The scenario captures the structural trap of colonial Deccan agriculture: global market dependence (cotton boom/bust), usurious lending practices, a colonial legal system that enforced debt contracts without considering the power imbalance, and the absence of protective legislation (the Relief Act came only in 1879).",
    "difficulty": "hard",
    "bloom_level": "analyse",
    "subject": "history",
    "chapter_id": "cuet-hist-colonialism",
    "chapter": "Colonialism and the Countryside",
    "topic": "Colonialism and the Countryside",
    "exam_suitability": [
      "CUET"
    ],
    "question_text": "Scenario: In 1862, a Deccan peasant borrows ₹100 from a sahukar at 30% compound interest to expand cotton cultivation. Cotton prices are high due to the American Civil War. By 1866, the war is over, cotton prices have crashed, and the peasant's debt has grown to ₹285 with accumulated interest and charges. The peasant cannot repay, and the sahukar obtains a court decree to seize the peasant's five-acre plot.\n\nWhich structural factors explain this peasant's dispossession?",
    "question_type": "scenario-based",
    "elimination_hints": [],
    "concept_tags": [],
    "subtopic": ""
  },
  {
    "id": "cuet-hist-col-69",
    "options": [
      {
        "key": "A",
        "text": "It created a classless egalitarian society",
        "is_correct": false
      },
      {
        "key": "B",
        "text": "It consolidated a class of absentee zamindars, empowered jotedars locally, and left cultivators and sharecroppers at the bottom of a deeply stratified hierarchy",
        "is_correct": true
      },
      {
        "key": "C",
        "text": "It eliminated all zamindars and gave land to peasants",
        "is_correct": false
      },
      {
        "key": "D",
        "text": "It had no lasting impact on Bengal's social structure",
        "is_correct": false
      }
    ],
    "correct_answer": "B",
    "explanation": "The Permanent Settlement restructured Bengal's rural society: zamindars became absentee rent-collectors, jotedars emerged as the real power at the local level, and actual cultivators (ryots) and sharecroppers (bargadars) bore the heaviest burdens with the least rights — a hierarchy that persisted well into the 20th century.",
    "difficulty": "hard",
    "bloom_level": "analyse",
    "subject": "history",
    "chapter_id": "cuet-hist-colonialism",
    "chapter": "Colonialism and the Countryside",
    "topic": "Colonialism and the Countryside",
    "exam_suitability": [
      "CUET"
    ],
    "question_text": "What was the long-term impact of the Permanent Settlement on Bengal's rural class structure?",
    "question_type": "mcq",
    "elimination_hints": [],
    "concept_tags": [],
    "subtopic": ""
  },
  {
    "id": "cuet-hist-col-70",
    "options": [
      {
        "key": "A",
        "text": "The diagram shows that cultivators benefited most because they were closest to the land and kept all the produce",
        "is_correct": false
      },
      {
        "key": "B",
        "text": "The system created layered extraction: the Company took fixed revenue from zamindars, zamindars extracted rent through intermediaries, intermediaries each kept a margin, and moneylenders trapped cultivators in debt — with cultivators at the bottom bearing the cumulative burden of all layers",
        "is_correct": true
      },
      {
        "key": "C",
        "text": "The diagram shows that zamindars bore the greatest burden because they had to pay fixed revenue",
        "is_correct": false
      },
      {
        "key": "D",
        "text": "The system was egalitarian with all levels sharing the agricultural surplus equally",
        "is_correct": false
      }
    ],
    "correct_answer": "B",
    "explanation": "The diagram illustrates how the Permanent Settlement created a hierarchy of extraction. The Company received fixed revenue at the top. Zamindars, to meet demands and profit, extracted rent — often through multiple sub-tenure layers that each took a cut. The cultivator at the bottom paid the cumulative cost and, when unable to meet demands, fell into the clutches of moneylenders who could seize land through colonial courts and even purchase zamindari estates at auction, completing a cycle of dispossession.",
    "difficulty": "hard",
    "bloom_level": "analyse",
    "subject": "history",
    "chapter_id": "cuet-hist-colonialism",
    "chapter": "Colonialism and the Countryside",
    "topic": "Colonialism and the Countryside",
    "exam_suitability": [
      "CUET"
    ],
    "image": "images/cuet-hist-col-70.svg",
    "question_text": "Study the diagram below showing the flow of revenue and exploitation under the Permanent Settlement in Bengal.\n\n[DIAGRAM: A vertical flowchart with five levels. Top: 'EAST INDIA COMPANY (State)' with label 'Receives fixed permanent revenue'. Arrow down (labelled 'Fixed Revenue Demand') to Level 2: 'ZAMINDAR (Proprietor)' with labels 'Can be auctioned if default (Sunset Law)' and 'Keeps surplus above fixed demand'. Arrow down (labelled 'Rent Extraction') to Level 3: 'SUB-TENURES / INTERMEDIARIES' showing 3 nested boxes representing layers of sub-infeudation, each with arrow and label 'Rent passed up, margin kept'. Arrow down to Level 4: 'RYOT (Cultivator)' with labels 'Bears highest burden', 'No legal protection initially', 'Often borrows from moneylender'. A separate arrow from Level 4 goes sideways to a box: 'MONEYLENDER' with label 'Provides credit at high interest; can seize land through courts'. A dotted arrow from Moneylender loops back to Zamindar level labelled 'Buys auctioned estates'.]\n\nBased on the diagram, explain how the system created a cycle where the actual cultivator bore the greatest burden while multiple groups extracted surplus from agricultural production.",
    "question_type": "diagram-based",
    "elimination_hints": [],
    "concept_tags": [],
    "subtopic": ""
  }
]